pycodemark/__init__.py
pycodemark/analyzer.py
pycodemark/config.py
pycodemark/console.py
pycodemark/evaluator.py
pycodemark/plugins.py
pycodemark/renderer.py
pycodemark/reporter.py
pycodemark/sample_plugin.py
pycodemark/smart_reviewer.py
pycodemark/version.py
pycodemark-0.4.1.dist-info/LICENSE
pycodemark-0.4.1.dist-info/METADATA
pycodemark-0.4.1.dist-info/WHEEL
pycodemark-0.4.1.dist-info/entry_points.txt
pycodemark-0.4.1.dist-info/RECORD
