Metadata-Version: 2.3
Name: pycodemark
Version: 0.4.1
Summary: PyCodemark – a full-featured code review tool for Python.
License: MIT
Keywords: python,code,review,linter,cli,static-analysis,quality
Author: Roshan
Author-email: roshanguptamca@gmail.com
Requires-Python: >=3.13
Classifier: Development Status :: 4 - Beta
Classifier: Intended Audience :: Developers
Classifier: License :: OSI Approved :: MIT License
Classifier: Operating System :: OS Independent
Classifier: Programming Language :: Python :: 3
Classifier: Programming Language :: Python :: 3.13
Classifier: Topic :: Software Development :: Quality Assurance
Classifier: Topic :: Utilities
Requires-Dist: openai (>=2.6.1,<3.0.0)
Requires-Dist: rich (>=14.0,<15.0)
Requires-Dist: tomli (>=2.0,<3.0)
Project-URL: Documentation, https://github.com/roshanguptamca/pycodemark/blob/main/README.md
Project-URL: Homepage, https://github.com/roshanguptamca/pycodemark/
Project-URL: Repository, https://github.com/roshanguptamca/pycodemark/
